Metadata-Version: 1.0
Name: password-creator
Version: 1.2.0
Summary: Create random passwords from the command line
Home-page: https://github.com/patrickleweryharris/password_creator
Author: Patrick Lewery Harris
Author-email: patrick@plh.io
License: UNKNOWN
Platform: UNKNOWN
